stamina/__init__.py
stamina/_config.py
stamina/_core.py
stamina/py.typed
stamina/typing.py
stamina/instrumentation/__init__.py
stamina/instrumentation/_data.py
stamina/instrumentation/_hooks.py
stamina/instrumentation/_logging.py
stamina/instrumentation/_prometheus.py
stamina/instrumentation/_structlog.py
stamina-24.2.0.dist-info/METADATA
stamina-24.2.0.dist-info/WHEEL
stamina-24.2.0.dist-info/licenses/LICENSE
stamina-24.2.0.dist-info/RECORD
