Metadata-Version: 2.1
Name: stamina
Version: 24.2.0
Summary: Production-grade retries made easy.
Project-URL: Documentation, https://stamina.hynek.me/
Project-URL: Source, https://github.com/hynek/stamina
Project-URL: Changelog, https://github.com/hynek/stamina/blob/main/CHANGELOG.md
Project-URL: Funding, https://github.com/sponsors/hynek
Project-URL: Mastodon, https://mastodon.social/@hynek
Project-URL: Twitter, https://twitter.com/hynek
Author-email: Hynek Schlawack <hs@ox.cx>
License-Expression: MIT
License-File: LICENSE
Keywords: reliability,retries,retry
Classifier: Development Status :: 5 - Production/Stable
Classifier: Framework :: AsyncIO
Classifier: Framework :: Trio
Classifier: License :: OSI Approved :: MIT License
Classifier: Programming Language :: Python :: 3.8
Classifier: Programming Language :: Python :: 3.9
Classifier: Programming Language :: Python :: 3.10
Classifier: Programming Language :: Python :: 3.11
Classifier: Programming Language :: Python :: 3.12
Classifier: Typing :: Typed
Requires-Python: >=3.8
Requires-Dist: tenacity
Requires-Dist: typing-extensions; python_version < '3.10'
Provides-Extra: dev
Requires-Dist: nox; extra == 'dev'
Requires-Dist: prometheus-client; extra == 'dev'
Requires-Dist: stamina[tests,typing]; extra == 'dev'
Requires-Dist: structlog; extra == 'dev'
Requires-Dist: tomli; (python_version < '3.11') and extra == 'dev'
Requires-Dist: trio; extra == 'dev'
Provides-Extra: docs
Requires-Dist: furo; extra == 'docs'
Requires-Dist: myst-parser; extra == 'docs'
Requires-Dist: prometheus-client; extra == 'docs'
Requires-Dist: sphinx-copybutton; extra == 'docs'
Requires-Dist: sphinx-notfound-page; extra == 'docs'
Requires-Dist: sphinx>=7.2.2; extra == 'docs'
Requires-Dist: structlog; extra == 'docs'
Provides-Extra: tests
Requires-Dist: anyio; extra == 'tests'
Requires-Dist: pytest; extra == 'tests'
Provides-Extra: typing
Requires-Dist: mypy>=1.4; extra == 'typing'
